tests/__init__.py
tests/test_advanced_cleaner.py
tests/test_cleaner.py
tests/test_cleaner_v1.py
tests/test_document_processor.py
tests/test_performance_cleaner.py
tests/test_spell_checker.py
text_cleaner_for_py/__init__.py
text_cleaner_for_py/advanced_cleaner.py
text_cleaner_for_py/cleaner.py
text_cleaner_for_py/cleaner_v1.py
text_cleaner_for_py/config.py
text_cleaner_for_py/document_processor.py
text_cleaner_for_py/exceptions.py
text_cleaner_for_py/logging_config.py
text_cleaner_for_py/performance_cleaner.py
text_cleaner_for_py/spell_checker.py
text_cleaner_for_py-1.5.0.dist-info/licenses/LICENSE
text_cleaner_for_py-1.5.0.dist-info/METADATA
text_cleaner_for_py-1.5.0.dist-info/WHEEL
text_cleaner_for_py-1.5.0.dist-info/top_level.txt
text_cleaner_for_py-1.5.0.dist-info/RECORD
