Metadata-Version: 2.4
Name: text_cleaner_for_py
Version: 1.5.0
Summary: ​💬​ Uma biblioteca Python para limpeza e processamento de texto
Home-page: https://github.com/seu-usuario/text_cleaner
Author: Roberto Lima
Author-email: robertolima@example.com
License: MIT
Project-URL: Homepage, https://github.com/robertolima-dev/text-cleaner-for-py
Project-URL: Repository, https://github.com/robertolima-dev/text-cleaner-for-py
Project-URL: Issues, https://github.com/robertolima-dev/text-cleaner-for-py/issues
Requires-Python: >=3.8
License-File: LICENSE
Requires-Dist: nltk>=3.8.1
Requires-Dist: beautifulsoup4>=4.12.2
Requires-Dist: emoji>=2.8.0
Requires-Dist: langdetect>=1.0.9
Requires-Dist: torch>=2.0.0
Requires-Dist: redis>=4.5.0
Requires-Dist: pyspellchecker>=0.7.2
Requires-Dist: PyPDF2>=3.0.0
Requires-Dist: python-docx>=0.8.11
Requires-Dist: numpy>=1.24.0
Provides-Extra: dev
Requires-Dist: pytest>=7.4.0; extra == "dev"
Requires-Dist: pytest-asyncio>=0.21.1; extra == "dev"
Requires-Dist: pytest-cov>=4.1.0; extra == "dev"
Requires-Dist: pytest-benchmark>=4.0.0; extra == "dev"
Requires-Dist: pytest-mock>=3.11.1; extra == "dev"
Requires-Dist: pytest-timeout>=2.1.0; extra == "dev"
Requires-Dist: pytest-xdist>=3.3.1; extra == "dev"
Requires-Dist: pytest-sugar>=0.9.7; extra == "dev"
Requires-Dist: pytest-html>=4.1.1; extra == "dev"
Requires-Dist: pytest-metadata>=3.0.0; extra == "dev"
Requires-Dist: pytest-env>=1.1.1; extra == "dev"
Requires-Dist: pytest-randomly>=3.12.0; extra == "dev"
Requires-Dist: pytest-repeat>=0.9.1; extra == "dev"
Requires-Dist: pytest-rerunfailures>=12.0; extra == "dev"
Requires-Dist: black>=23.0.0; extra == "dev"
Requires-Dist: isort>=5.12.0; extra == "dev"
Requires-Dist: mypy>=1.0.0; extra == "dev"
Requires-Dist: flake8>=6.0.0; extra == "dev"
Requires-Dist: pre-commit>=3.0.0; extra == "dev"
Dynamic: author
Dynamic: author-email
Dynamic: home-page
Dynamic: license-file
Dynamic: requires-python
